fastseq/__init__.py
fastseq/config.py
fastseq/logging/__init__.py
fastseq/logging/logging_utils.py
fastseq/optimizer/__init__.py
fastseq/optimizer/fairseq/__init__.py
fastseq/optimizer/fairseq/beam_search_optimizer.py
fastseq/optimizer/fairseq/beam_search_optimizer_v1.py
fastseq/optimizer/fairseq/beam_search_optimizer_v2.py
fastseq/optimizer/fairseq/generate_v1.py
fastseq/optimizer/fairseq/generate_v2.py
fastseq/optimizer/transformers/__init__.py
fastseq/optimizer/transformers/beam_search_optimizer.py
fastseq/optimizer/transformers/modeling_bart_optimizer_2_11_0.py
fastseq/optimizer/transformers/modeling_t5_optimizer.py
fastseq/utils/__init__.py
fastseq/utils/api_decorator.py
fastseq/utils/file_utils.py
fastseq/utils/test_utils.py
fastseq_cli/__init__.py
fastseq_cli/eval_lm.py
fastseq_cli/generate.py
fastseq_cli/transformers_generate.py
fastseq_cli/transformers_utils.py
tests/models/__init__.py
tests/models/test_prophetnet_fs.py
tests/optimizer/__init__.py
tests/optimizer/fairseq/__init__.py
tests/optimizer/fairseq/benchmark_fairseq_optimizer.py
tests/optimizer/fairseq/test_fairseq_optimizer.py
tests/utils/__init__.py
tests/utils/test_api_decorator.py
tests/utils/test_file_utils.py
fastseq-0.0.3.dist-info/LICENSE
fastseq-0.0.3.dist-info/METADATA
fastseq-0.0.3.dist-info/WHEEL
fastseq-0.0.3.dist-info/entry_points.txt
fastseq-0.0.3.dist-info/top_level.txt
fastseq-0.0.3.dist-info/RECORD
