Metadata-Version: 2.1
Name: fastseq
Version: 0.0.3
Summary: Efficient implementations of sequence models with fast performance
Home-page: https://github.com/microsoft/fastseq
Author: Microsft AdsBrain Team
Author-email: fastseq@microsoft.com
License: MIT
Keywords: NLP NLG deep learning transformer sequence pytorch tensorflow BERT GPT GPT-2 Microsoft
Platform: UNKNOWN
Classifier: Development Status :: 5 - Production/Stable
Classifier: Intended Audience :: Developers
Classifier: Intended Audience :: Education
Classifier: Intended Audience :: Science/Research
Classifier: License :: OSI Approved :: MIT License
Classifier: Operating System :: OS Independent
Classifier: Programming Language :: Python :: 3
Classifier: Programming Language :: Python :: 3.6
Classifier: Programming Language :: Python :: 3.7
Classifier: Topic :: Scientific/Engineering :: Artificial Intelligence
Requires-Python: >=3.6.0
Requires-Dist: absl-py
Requires-Dist: numpy
Requires-Dist: requests
Requires-Dist: packaging
Provides-Extra: fairseq
Requires-Dist: fairseq (>=0.9.0) ; extra == 'fairseq'
Provides-Extra: torch
Requires-Dist: torch (>=1.4.0) ; extra == 'torch'
Provides-Extra: transformers
Requires-Dist: transformers (>=3.0.2) ; extra == 'transformers'
